[
 {
  "170981835059232779": {
   "Discord_Name": "cadenv27",
   "Total_Deals_Amount": 5,
   "Total_Deals_Completed": 74
  }
 },
 {
  "431513934164393985": {
   "Discord_Name": "KANgers",
   "Total_Deals_Amount": 20,
   "Total_Deals_Completed": 0
  }
 },
 {
  "477266267175256125": {
   "Discord_Name": "Neth",
   "Total_Deals_Amount": 0,
   "Total_Deals_Completed": 0
  }
 },
 {
  "361815100576890890": {
   "Discord_Name": "Beetlemadooda",
   "Total_Deals_Amount": 30,
   "Total_Deals_Completed": 2
  }
 },
 {
  "573409733353013249": {
   "Discord_Name": "ILIATDM",
   "Total_Deals_Amount": "30",
   "Total_Deals_Completed": "1"
  }
 }
]